avoine/__init__.py
avoine/avoine.py
avoine/py.typed
avoine-0.1.0a1.dist-info/WHEEL
avoine-0.1.0a1.dist-info/METADATA
avoine-0.1.0a1.dist-info/RECORD
