Metadata-Version: 2.4
Name: avoine
Version: 0.1.0a1
Summary: Tiny serialisation and deserialisation library
Author: classabbyamp
Author-email: classabbyamp <dev@placeviolette.net>
License-Expression: CC0-1.0
Classifier: Development Status :: 5 - Production/Stable
Classifier: Intended Audience :: Developers
Classifier: Programming Language :: Python :: 3
Classifier: Programming Language :: Python :: 3.12
Classifier: Programming Language :: Python :: 3.13
Classifier: Programming Language :: Python :: 3.14
Classifier: Topic :: File Formats
Classifier: Typing :: Typed
Requires-Python: >=3.12
Project-URL: homepage, https://codeberg.org/classabbyamp/avoine
Project-URL: issues, https://codeberg.org/classabbyamp/avoine/issues
Project-URL: source, https://codeberg.org/classabbyamp/avoine
